{
    "_defaults": ["Frutas","Animais","Países","Desportos","Profissões","Veículos","Sobremesas","Cores","Instrumentos","Objetos Domésticos","Clima"],
    "Frutas": ["Maçã","Banana","Laranja","Uva","Manga","Pêra","Pêssego","Kiwi","Ananás","Ameixa","Cereja","Melancia","Melão","Maracujá"],
    "Animais": ["Gato","Cão","Leão","Tigre","Elefante","Zebra","Girafa","Baleia","Tubarão","Águia","Panda"],
    "Países": ["Portugal","Espanha","França","Alemanha","Itália","Brasil","Japão","Canadá","Austrália","Egito","USA","México"],
    "Desportos": ["Futebol","Basquetebol","Ténis","Golfe","Rúgbi","Padel","Voleibol","Natação","Ciclismo","Boxe","Hóquei","Basebol"],
    "Profissões": ["Médico","Professor","Engenheiro","Artista","Chefe","Piloto","Enfermeiro","Agricultor","Escritor","Advogado","Músico","Bombeiro"],
    "Veículos": ["Carro","Autocarro","Bicicleta","Mota","Comboio","Avião","Navio","Submarino","Helicóptero","Trotinete","Carrinha","Camião"],
    "Sobremesas": ["Bolo","Gelado","Bolacha","Brownie","Tarte","Pudim","Tarte","Mousse","Cheesecake","Donut","Pastel De Nata"],
    "Cores": ["Vermelho","Azul","Verde","Amarelo","Violeta","Laranja","Rosa","Castanho","Preto","Branco","Cinzento","Turquesa"],
    "Instrumentos": ["Guitarra","Piano","Violino","Bateria","Flauta","Trompete","Saxofone","Violoncelo","Harpa","Clarinete","Ukulele"],
    "Objetos Domésticos": ["Colher","Garfo","Faca","Prato","Copo","Sofá","Lâmpada","Espelho","Toalha","Almofada","Vassoura"],
    "Clima": ["Chuva","Neve","Sol","Nublado","Tempestade","Nevoeiro","Granizo","Trovoada"],
    "OGs": ["André","Ema","João","Joana","Ricardo"],
    "LoL champions": ["Aatrox","Ahri","Akali","Akshan","Alistar","Ambessa","Amumu","Anivia","Annie","Aphelios","Ashe","Aurelion Sol","Aurora","Azir","Bard","Bel'Veth","Blitzcrank","Brand","Braum","Briar","Caitlyn","Camille","Cassiopeia","Cho'Gath","Corki","Darius","Diana","Dr. Mundo","Draven","Ekko","Elise","Evelynn","Ezreal","Fiddlesticks","Fiora","Fizz","Galio","Gangplank","Garen","Gnar","Gragas","Graves","Gwen","Hecarim","Heimerdinger","Hwei","Illaoi","Irelia","Ivern","Janna","Jarvan IV","Jax","Jayce","Jhin","Jinx","K'Sante","Kai'Sa","Kalista","Karma","Karthus","Kassadin","Katarina","Kayle","Kayn","Kennen","Kha'Zix","Kindred","Kled","Kog'Maw","LeBlanc","Lee Sin","Leona","Lillia","Lissandra","Lucian","Lulu","Lux","Malphite","Malzahar","Maokai","Master Yi","Mel","Milio","Miss Fortune","Mordekaiser","Morgana","Naafiri","Nami","Nasus","Nautilus","Neeko","Nidalee","Nilah","Nocturne","Nunu & Willump","Olaf","Orianna","Ornn","Pantheon","Poppy","Pyke","Qiyana","Quinn","Rakan","Rammus","Rek'Sai","Rell","Renata Glasc","Renekton","Rengar","Riven","Rumble","Ryze","Samira","Sejuani","Senna","Seraphine","Sett","Shaco","Shen","Shyvana","Singed","Sion","Sivir","Skarner","Smolder","Sona","Soraka","Swain","Sylas","Syndra","Tahm Kench","Taliyah","Talon","Taric","Teemo","Thresh","Tristana","Trundle","Tryndamere","Twisted Fate","Twitch","Udyr","Urgot","Varus","Vayne","Veigar","Vel'Koz","Vex","Vi","Viego","Viktor","Vladimir","Volibear","Warwick","Wukong","Xayah","Xerath","Xin Zhao","Yasuo","Yone","Yorick","Yunara","Yuumi","Zac","Zed","Zeri","Ziggs","Zilean","Zoe","Zyra"]
}